rest_framework_vault/__init__.py
rest_framework_vault/parsers.py
rest_framework_vault/renderers.py
rest_framework_vault/utils.py
django_rest_vault-0.0.3.dist-info/LICENSE
django_rest_vault-0.0.3.dist-info/METADATA
django_rest_vault-0.0.3.dist-info/WHEEL
django_rest_vault-0.0.3.dist-info/top_level.txt
django_rest_vault-0.0.3.dist-info/RECORD
