Metadata-Version: 2.1
Name: django-rest-vault
Version: 0.0.3
Summary: Api data decryption and encryption support for Django REST Framework
Home-page: https://github.com/wlemuel/django-rest-vault
Author: Steve Lemuel
Author-email: wlemuel@hotmail.com
License: MIT License
Keywords: drf django django-rest-framework
Classifier: Environment :: Web Environment
Classifier: Framework :: Django
Classifier: Framework :: Django :: 2.2
Classifier: Framework :: Django :: 3.0
Classifier: Framework :: Django :: 3.1
Classifier: Framework :: Django :: 3.2
Classifier: Framework :: Django :: 4.0
Classifier: Framework :: Django :: 4.1
Classifier: Intended Audience :: Developers
Classifier: License :: OSI Approved :: MIT License
Classifier: Operating System :: OS Independent
Classifier: Programming Language :: Python
Classifier: Programming Language :: Python :: 3.6
Classifier: Programming Language :: Python :: 3.7
Classifier: Programming Language :: Python :: 3.8
Classifier: Programming Language :: Python :: 3.9
Classifier: Programming Language :: Python :: 3.10
Classifier: Programming Language :: Python :: 3.11
Classifier: Topic :: Internet :: WWW/HTTP
Classifier: Topic :: Internet :: WWW/HTTP :: Dynamic Content
License-File: LICENSE
Requires-Dist: Django (>=2.2.16)
Requires-Dist: djangorestframework (>=3.10.3)
Requires-Dist: pycryptodome (>=3.9.1)
